{"9-scn":{"confType":"auto"},"11-scn":{"confType":"auto"},"10-scn":{"confType":"auto"},"362":{"confType":"auto"},"352":{"confType":"auto"},"357":{"confType":"auto"},"285":{"confType":"auto"},"762":{"confType":"man","type":"DevRGBLight","params":{"status":{"cmdId":"758"},"energy":{"cmdId":"758"},"level":{"cmdId":"758"},"dimmable":{"value":"0"},"whitechannel":{"value":"0"},"color":{"cmdId":"762"}},"actions":{"setStatus":{"type":"item","options":{"0":{"cmdId":"","cmdParam":""},"1":{"cmdId":"","cmdParam":""}}},"setLevel":{"type":"direct","options":{"cmdId":"760"}},"setColor":{"type":"direct","options":{"cmdId":"763"}}}},"271":{"confType":"auto"},"291":{"confType":"auto"},"410":{"confType":"auto"},"295":{"confType":"auto"},"303":{"confType":"auto"},"415":{"confType":"auto"},"431":{"confType":"auto"},"299":{"confType":"auto"},"340":{"confType":"auto"},"307":{"confType":"auto"},"311":{"confType":"auto"},"446":{"confType":"auto"},"418":{"confType":"man","type":"DevSwitch","params":{"status":{"cmdId":"418"},"energy":{"cmdId":""}},"actions":{"setStatus":{"type":"item","options":{"0":{"cmdId":"417","cmdParam":""},"1":{"cmdId":"416","cmdParam":""}}}}},"421":{"confType":"man","type":"DevSwitch","params":{"status":{"cmdId":"421"},"energy":{"cmdId":""}},"actions":{"setStatus":{"type":"item","options":{"0":{"cmdId":"420","cmdParam":""},"1":{"cmdId":"419","cmdParam":""}}}}},"344":{"confType":"man","type":"DevSwitch","params":{"status":{"cmdId":"344"},"energy":{"cmdId":""}},"actions":{"setStatus":{"type":"item","options":{"0":{"cmdId":"343","cmdParam":""},"1":{"cmdId":"342","cmdParam":""}}}}},"347":{"confType":"man","type":"DevSwitch","params":{"status":{"cmdId":"347"},"energy":{"cmdId":""}},"actions":{"setStatus":{"type":"item","options":{"0":{"cmdId":"346","cmdParam":""},"1":{"cmdId":"345","cmdParam":""}}}}},"508":{"confType":"man","type":"DevSwitch","params":{"status":{"cmdId":"508"},"energy":{"cmdId":""}},"actions":{"setStatus":{"type":"item","options":{"0":{"cmdId":"507","cmdParam":""},"1":{"cmdId":"506","cmdParam":""}}}}},"424":{"confType":"man","type":"DevSwitch","params":{"status":{"cmdId":"424"},"energy":{"cmdId":""}},"actions":{"setStatus":{"type":"item","options":{"0":{"cmdId":"423","cmdParam":""},"1":{"cmdId":"422","cmdParam":""}}}}},"440":{"confType":"man","type":"DevSwitch","params":{"status":{"cmdId":"440"},"energy":{"cmdId":""}},"actions":{"setStatus":{"type":"item","options":{"0":{"cmdId":"439","cmdParam":""},"1":{"cmdId":"438","cmdParam":""}}}}},"443":{"confType":"man","type":"DevSwitch","params":{"status":{"cmdId":"443"},"energy":{"cmdId":""}},"actions":{"setStatus":{"type":"item","options":{"0":{"cmdId":"442","cmdParam":""},"1":{"cmdId":"441","cmdParam":""}}}}},"511":{"confType":"man","type":"DevSwitch","params":{"status":{"cmdId":"511"},"energy":{"cmdId":""}},"actions":{"setStatus":{"type":"item","options":{"0":{"cmdId":"510","cmdParam":""},"1":{"cmdId":"509","cmdParam":""}}}}},"434":{"confType":"man","type":"DevSwitch","params":{"status":{"cmdId":"434"},"energy":{"cmdId":""}},"actions":{"setStatus":{"type":"item","options":{"0":{"cmdId":"433","cmdParam":""},"1":{"cmdId":"432","cmdParam":""}}}}},"776":{"confType":"man","type":"DevSwitch","params":{"status":{"cmdId":"776"},"energy":{"cmdId":"775"}},"actions":{"setStatus":{"type":"item","options":{"0":{"cmdId":"774","cmdParam":""},"1":{"cmdId":"774","cmdParam":""}}}}},"403":{"confType":"auto"},"795":{"confType":"auto"},"799":{"confType":"auto"},"3":{"confType":"auto"}}